{
  "recentFiles": [
    {
      "basename": "Back-end MOC",
      "path": "Atlas/Maps/Back-end MOC.md"
    },
    {
      "basename": "DotNet",
      "path": "Atlas/Maps/DotNet.md"
    },
    {
      "basename": "CSharp MOC",
      "path": "Atlas/Maps/CSharp MOC.md"
    },
    {
      "basename": "Cs Value and Reference Types",
      "path": "Atlas/Notes/Ideas/Programming/DotNet/CSharp/Cs Value and Reference Types.md"
    },
    {
      "basename": "Cs Constructor",
      "path": "Atlas/Notes/Ideas/Programming/DotNet/CSharp/Cs Constructor.md"
    },
    {
      "basename": "CSharp Struct",
      "path": "+/CSharp Struct.md"
    },
    {
      "basename": "Cs System.Object",
      "path": "Atlas/Notes/Ideas/Programming/DotNet/CSharp/Cs System.Object.md"
    },
    {
      "basename": "Cs Struct",
      "path": "Atlas/Notes/Ideas/Programming/DotNet/CSharp/Cs Struct.md"
    },
    {
      "basename": "Cs Boxing and Unboxing",
      "path": "Atlas/Notes/Ideas/Programming/DotNet/CSharp/Cs Boxing and Unboxing.md"
    },
    {
      "basename": "Cs Variables",
      "path": "Atlas/Notes/Ideas/Programming/DotNet/CSharp/Cs Variables.md"
    },
    {
      "basename": "Cs Data Types",
      "path": "Atlas/Notes/Ideas/Programming/DotNet/CSharp/Cs Data Types.md"
    },
    {
      "basename": "Cs Properties",
      "path": "Atlas/Notes/Ideas/Programming/DotNet/CSharp/Cs Properties.md"
    },
    {
      "basename": "Cs Class",
      "path": "Atlas/Notes/Ideas/Programming/DotNet/CSharp/Cs Class.md"
    },
    {
      "basename": "Cs Access Modifiers",
      "path": "Atlas/Notes/Ideas/Programming/DotNet/CSharp/Cs Access Modifiers.md"
    },
    {
      "basename": "Cs Indexer",
      "path": "Atlas/Notes/Ideas/Programming/DotNet/CSharp/Cs Indexer.md"
    },
    {
      "basename": "Cs Encapsulation",
      "path": "Atlas/Notes/Ideas/Programming/DotNet/CSharp/Cs Encapsulation.md"
    },
    {
      "basename": "Cs Null",
      "path": "Atlas/Notes/Ideas/Programming/DotNet/CSharp/Cs Null.md"
    },
    {
      "basename": "CSharp Protective code",
      "path": "Atlas/Notes/Ideas/Programming/DotNet/CSharp/CSharp Protective code.md"
    },
    {
      "basename": "Library",
      "path": "Atlas/Maps/Library.md"
    },
    {
      "basename": "Home",
      "path": "Home.md"
    },
    {
      "basename": "المحاضرة الثانية-دورة الإيمان",
      "path": "+/المحاضرة الثانية-دورة الإيمان.md"
    },
    {
      "basename": "دورة الإيمان",
      "path": "+/دورة الإيمان.md"
    },
    {
      "basename": "المحاضرة الأولى-دورة الإيمان",
      "path": "+/المحاضرة الأولى-دورة الإيمان.md"
    },
    {
      "basename": "Rana Session",
      "path": "Atlas/Notes/Ideas/Social Media/Rana Session.md"
    },
    {
      "basename": "المبادئ العشرة",
      "path": "Atlas/Notes/Ideas/البناء المنهجي/المبادئ العشرة.md"
    },
    {
      "basename": "Binary Search",
      "path": "Atlas/Notes/Ideas/Programming/Problem Solving/Binary Search.md"
    },
    {
      "basename": "Problem Solving",
      "path": "Atlas/Maps/Problem Solving.md"
    },
    {
      "basename": "Programming MOC",
      "path": "Atlas/Maps/Programming MOC.md"
    },
    {
      "basename": "Data Structure and Algorithms MOC",
      "path": "Atlas/Maps/Data Structure and Algorithms MOC.md"
    },
    {
      "basename": "Prefix Sums",
      "path": "Atlas/Notes/Ideas/Programming/Data Structure and Algorithms/Prefix Sums.md"
    },
    {
      "basename": "Cs Enums",
      "path": "Atlas/Notes/Ideas/Programming/DotNet/CSharp/Cs Enums.md"
    },
    {
      "basename": "Innotech Intern",
      "path": "+/Innotech Intern.md"
    },
    {
      "basename": "Cs Type Casting",
      "path": "Atlas/Notes/Ideas/Programming/DotNet/CSharp/Cs Type Casting.md"
    },
    {
      "basename": "Cs Handle Exception",
      "path": "Atlas/Notes/Ideas/Programming/DotNet/CSharp/Cs Handle Exception.md"
    },
    {
      "basename": "VS Secrets",
      "path": "Atlas/Notes/Ideas/Programming/DotNet/CSharp/VS Secrets.md"
    },
    {
      "basename": "Encapsulation",
      "path": "Atlas/Notes/Ideas/Programming/OOP/Encapsulation.md"
    },
    {
      "basename": "Cs Arrays",
      "path": "Atlas/Notes/Ideas/Programming/DotNet/CSharp/Cs Arrays.md"
    },
    {
      "basename": "Cs Input",
      "path": "Atlas/Notes/Ideas/Programming/DotNet/CSharp/Cs Input.md"
    },
    {
      "basename": "Cs Output",
      "path": "Atlas/Notes/Ideas/Programming/DotNet/CSharp/Cs Output.md"
    },
    {
      "basename": "Cs Library vs Console App",
      "path": "Atlas/Notes/Ideas/Programming/DotNet/CSharp/Cs Library vs Console App.md"
    },
    {
      "basename": "CLS and CTS",
      "path": "Atlas/Notes/Ideas/Programming/DotNet/CSharp/CLS and CTS.md"
    },
    {
      "basename": "Programming Paradigms",
      "path": "Atlas/Notes/Ideas/Programming/Topics/Programming Paradigms.md"
    },
    {
      "basename": "OOP",
      "path": "Atlas/Notes/Ideas/Programming/OOP/OOP.md"
    },
    {
      "basename": "DotNet Story",
      "path": "Atlas/Notes/Ideas/Programming/DotNet/DotNet Story.md"
    },
    {
      "basename": "Lower and Upper Bound",
      "path": "Atlas/Notes/Ideas/Programming/Problem Solving/Lower and Upper Bound.md"
    },
    {
      "basename": "Reading problem statement",
      "path": "Atlas/Notes/Ideas/Programming/Problem Solving/Reading problem statement.md"
    },
    {
      "basename": "Tackling a problem",
      "path": "+/Tackling a problem.md"
    },
    {
      "basename": "HTML",
      "path": "Atlas/Maps/HTML.md"
    },
    {
      "basename": "Front-end MOC",
      "path": "Atlas/Maps/Front-end MOC.md"
    },
    {
      "basename": "CSS",
      "path": "Atlas/Maps/CSS.md"
    }
  ],
  "omittedPaths": [],
  "maxLength": null,
  "openType": "tab"
}