{
  "main": {
    "id": "c4f7fdb608baf8e1",
    "type": "split",
    "children": [
      {
        "id": "e0b3ac0111659cd1",
        "type": "tabs",
        "children": [
          {
            "id": "11bdb289d28a6708",
            "type": "leaf",
            "pane-relief:history-v1": {
              "pos": 0,
              "stack": [
                {
                  "state": "{}",
                  "eState": "{}"
                }
              ]
            },
            "pinned": true,
            "state": {
              "type": "markdown",
              "state": {
                "file": "Home.md",
                "mode": "preview",
                "backlinks": true,
                "source": false
              },
              "pinned": true,
              "icon": "lucide-file",
              "title": "Home"
            }
          },
          {
            "id": "07fa579875045a46",
            "type": "leaf",
            "pane-relief:history-v1": {
              "pos": 0,
              "stack": [
                {
                  "state": "{}",
                  "eState": "{}"
                }
              ]
            },
            "pinned": true,
            "state": {
              "type": "markdown",
              "state": {
                "file": "+/DotNet - RoadMap.md",
                "mode": "source",
                "backlinks": true,
                "source": false
              },
              "pinned": true,
              "icon": "lucide-file",
              "title": "DotNet - RoadMap"
            }
          },
          {
            "id": "b7b97a52de2ff082",
            "type": "leaf",
            "pane-relief:history-v1": {
              "pos": 3,
              "stack": [
                {
                  "title": "Database Management System (DBMS)",
                  "icon": "lucide-file",
                  "state": "{\"type\":\"markdown\",\"state\":{\"file\":\"Atlas/Notes/Ideas/Programming/Database/Database Management System (DBMS).md\",\"mode\":\"source\",\"backlinks\":true,\"source\":false},\"icon\":\"lucide-file\",\"title\":\"Database Management System (DBMS)\"}",
                  "eState": "{\"cursor\":{\"from\":{\"line\":13,\"ch\":0},\"to\":{\"line\":13,\"ch\":0}},\"scroll\":7}"
                },
                {
                  "title": "Database MOC",
                  "icon": "lucide-file",
                  "state": "{\"type\":\"markdown\",\"state\":{\"file\":\"Atlas/Maps/Database MOC.md\",\"mode\":\"source\",\"backlinks\":true,\"source\":false},\"icon\":\"lucide-file\",\"title\":\"Database MOC\"}",
                  "eState": "{\"cursor\":{\"from\":{\"line\":19,\"ch\":16},\"to\":{\"line\":19,\"ch\":16}},\"scroll\":15.769345238095237}"
                },
                {
                  "title": "Database",
                  "icon": "lucide-file",
                  "state": "{\"type\":\"markdown\",\"state\":{\"file\":\"Atlas/Notes/Ideas/Programming/Database/Database.md\",\"mode\":\"source\",\"backlinks\":true,\"source\":false},\"icon\":\"lucide-file\",\"title\":\"Database\"}",
                  "eState": "{\"cursor\":{\"from\":{\"line\":91,\"ch\":68},\"to\":{\"line\":91,\"ch\":68}},\"scroll\":7}"
                },
                {
                  "state": "{}",
                  "eState": "{}"
                }
              ]
            },
            "state": {
              "type": "markdown",
              "state": {
                "file": "+/University App.md",
                "mode": "source",
                "backlinks": true,
                "source": false
              },
              "icon": "lucide-file",
              "title": "University App"
            }
          },
          {
            "id": "5b6c4b3ca94edfae",
            "type": "leaf",
            "pane-relief:history-v1": {
              "pos": 0,
              "stack": [
                {
                  "state": "{}",
                  "eState": "{}"
                },
                {
                  "title": "SQL Server MOC",
                  "icon": "lucide-file",
                  "state": "{\"type\":\"markdown\",\"state\":{\"file\":\"+/SQL Server MOC.md\",\"mode\":\"source\",\"backlinks\":true,\"source\":false},\"icon\":\"lucide-file\",\"title\":\"SQL Server MOC\"}",
                  "eState": "{\"cursor\":{\"from\":{\"line\":4,\"ch\":12},\"to\":{\"line\":4,\"ch\":12}},\"scroll\":0}"
                },
                {
                  "title": "Database MOC",
                  "icon": "lucide-file",
                  "state": "{\"type\":\"markdown\",\"state\":{\"file\":\"Atlas/Maps/Database MOC.md\",\"mode\":\"source\",\"backlinks\":true,\"source\":false},\"icon\":\"lucide-file\",\"title\":\"Database MOC\"}",
                  "eState": "{\"cursor\":{\"from\":{\"line\":35,\"ch\":10},\"to\":{\"line\":35,\"ch\":10}},\"scroll\":15.761904761904763}"
                },
                {
                  "title": "Logical Design (Mapping)",
                  "icon": "lucide-file",
                  "state": "{\"type\":\"markdown\",\"state\":{\"file\":\"Atlas/Notes/Ideas/Programming/Database/Logical Design (Mapping).md\",\"mode\":\"source\",\"backlinks\":true,\"source\":false},\"icon\":\"lucide-file\",\"title\":\"Logical Design (Mapping)\"}",
                  "eState": "{\"cursor\":{\"from\":{\"line\":6,\"ch\":0},\"to\":{\"line\":6,\"ch\":0}}}"
                },
                {
                  "title": "Database MOC",
                  "icon": "lucide-file",
                  "state": "{\"type\":\"markdown\",\"state\":{\"file\":\"Atlas/Maps/Database MOC.md\",\"mode\":\"source\",\"backlinks\":true,\"source\":false},\"icon\":\"lucide-file\",\"title\":\"Database MOC\"}",
                  "eState": "{\"cursor\":{\"from\":{\"line\":29,\"ch\":17},\"to\":{\"line\":29,\"ch\":17}},\"scroll\":17.945652173913043}"
                }
              ]
            },
            "state": {
              "type": "markdown",
              "state": {
                "file": "+/Constraints.md",
                "mode": "source",
                "backlinks": true,
                "source": false
              },
              "icon": "lucide-file",
              "title": "Constraints"
            }
          },
          {
            "id": "08469f6fd4c24997",
            "type": "leaf",
            "pane-relief:history-v1": {
              "pos": 0,
              "stack": [
                {
                  "state": "{}",
                  "eState": "{}"
                },
                {
                  "title": "Networking Fundamentals",
                  "icon": "lucide-file",
                  "state": "{\"type\":\"markdown\",\"state\":{\"file\":\"Atlas/Maps/Networking Fundamentals.md\",\"mode\":\"source\",\"backlinks\":true,\"source\":false},\"icon\":\"lucide-file\",\"title\":\"Networking Fundamentals\"}",
                  "eState": "{\"cursor\":{\"from\":{\"line\":19,\"ch\":10},\"to\":{\"line\":19,\"ch\":10}},\"scroll\":8}"
                },
                {
                  "title": "Networking Fundamentals",
                  "icon": "lucide-file",
                  "state": "{\"type\":\"markdown\",\"state\":{\"file\":\"+/Networking Fundamentals.md\",\"mode\":\"source\",\"backlinks\":true,\"source\":false},\"icon\":\"lucide-file\",\"title\":\"Networking Fundamentals\"}",
                  "eState": "{\"cursor\":{\"from\":{\"line\":6,\"ch\":0},\"to\":{\"line\":6,\"ch\":0}}}"
                },
                {
                  "title": "Get Product by Id Endpoint",
                  "icon": "lucide-file",
                  "state": "{\"type\":\"markdown\",\"state\":{\"file\":\"+/Get Product by Id Endpoint.md\",\"mode\":\"source\",\"backlinks\":true,\"source\":false},\"icon\":\"lucide-file\",\"title\":\"Get Product by Id Endpoint\"}",
                  "eState": "{\"cursor\":{\"from\":{\"line\":65,\"ch\":8},\"to\":{\"line\":65,\"ch\":8}},\"scroll\":6}"
                },
                {
                  "title": "Asp DotNet Core Web API",
                  "icon": "lucide-file",
                  "state": "{\"type\":\"markdown\",\"state\":{\"file\":\"Atlas/Notes/Ideas/Programming/DotNet/ASP/Asp DotNet Core Web API.md\",\"mode\":\"source\",\"backlinks\":true,\"source\":false},\"icon\":\"lucide-file\",\"title\":\"Asp DotNet Core Web API\"}",
                  "eState": "{\"cursor\":{\"from\":{\"line\":22,\"ch\":28},\"to\":{\"line\":22,\"ch\":28}},\"scroll\":19.0072202166065}"
                },
                {
                  "title": "Saving data from database in memory",
                  "icon": "lucide-file",
                  "state": "{\"type\":\"markdown\",\"state\":{\"file\":\"Atlas/Notes/Ideas/Programming/DotNet/ASP/Web API/Saving data from database in memory.md\",\"mode\":\"source\",\"backlinks\":true,\"source\":false},\"icon\":\"lucide-file\",\"title\":\"Saving data from database in memory\"}",
                  "eState": "{\"cursor\":{\"from\":{\"line\":6,\"ch\":0},\"to\":{\"line\":6,\"ch\":0}},\"scroll\":0}"
                }
              ]
            },
            "state": {
              "type": "markdown",
              "state": {
                "file": "+/Subnetting.md",
                "mode": "source",
                "backlinks": true,
                "source": false
              },
              "icon": "lucide-file",
              "title": "Subnetting"
            }
          },
          {
            "id": "debb8b2f13826740",
            "type": "leaf",
            "pane-relief:history-v1": {
              "pos": 0,
              "stack": [
                {
                  "state": "{}",
                  "eState": "{}"
                },
                {
                  "title": "Database MOC",
                  "icon": "lucide-file",
                  "state": "{\"type\":\"markdown\",\"state\":{\"file\":\"Atlas/Maps/Database MOC.md\",\"mode\":\"source\",\"backlinks\":true,\"source\":false},\"icon\":\"lucide-file\",\"title\":\"Database MOC\"}",
                  "eState": "{\"cursor\":{\"from\":{\"line\":33,\"ch\":16},\"to\":{\"line\":33,\"ch\":16}},\"scroll\":17.945652173913043}"
                }
              ]
            },
            "state": {
              "type": "markdown",
              "state": {
                "file": "+/Normalization.md",
                "mode": "source",
                "backlinks": true,
                "source": false
              },
              "icon": "lucide-file",
              "title": "Normalization"
            }
          },
          {
            "id": "dffaac5fd2a5f56c",
            "type": "leaf",
            "pane-relief:history-v1": {
              "pos": 0,
              "stack": [
                {
                  "state": "{}",
                  "eState": "{}"
                },
                {
                  "title": "Networking Fundamentals",
                  "icon": "lucide-file",
                  "state": "{\"type\":\"markdown\",\"state\":{\"file\":\"Atlas/Maps/Networking Fundamentals.md\",\"mode\":\"source\",\"backlinks\":true,\"source\":false},\"icon\":\"lucide-file\",\"title\":\"Networking Fundamentals\"}",
                  "eState": "{\"cursor\":{\"from\":{\"line\":10,\"ch\":9},\"to\":{\"line\":10,\"ch\":9}},\"scroll\":8}"
                }
              ]
            },
            "state": {
              "type": "markdown",
              "state": {
                "file": "Atlas/Notes/Ideas/Programming/Networking/Network Components.md",
                "mode": "source",
                "backlinks": true,
                "source": false
              },
              "icon": "lucide-file",
              "title": "Network Components"
            }
          }
        ],
        "currentTab": 6
      }
    ],
    "direction": "vertical"
  },
  "left": {
    "id": "440b3841429709ed",
    "type": "split",
    "children": [
      {
        "id": "b208c03cadd231ee",
        "type": "tabs",
        "dimension": 54.02597402597402,
        "children": [
          {
            "id": "dddbab8b18fd423a",
            "type": "leaf",
            "pane-relief:history-v1": {
              "pos": 0,
              "stack": [
                {
                  "state": "{}",
                  "eState": "{}"
                }
              ]
            },
            "state": {
              "type": "file-explorer",
              "state": {
                "sortOrder": "byCreatedTime"
              },
              "icon": "lucide-folder-closed",
              "title": "Files"
            }
          }
        ]
      },
      {
        "id": "f20ae5728f14bb8d",
        "type": "tabs",
        "dimension": 45.97402597402597,
        "children": [
          {
            "id": "bfacbb72bba173bf",
            "type": "leaf",
            "pane-relief:history-v1": {
              "pos": 0,
              "stack": [
                {
                  "state": "{}",
                  "eState": "{}"
                }
              ]
            },
            "state": {
              "type": "recent-files",
              "state": {},
              "icon": "clock",
              "title": "Recent Files"
            }
          },
          {
            "id": "1dc0cb1cebc39098",
            "type": "leaf",
            "pane-relief:history-v1": {
              "pos": 0,
              "stack": [
                {
                  "state": "{}",
                  "eState": "{}"
                }
              ]
            },
            "state": {
              "type": "calendar",
              "state": {},
              "icon": "calendar-with-checkmark",
              "title": "Calendar"
            }
          }
        ]
      }
    ],
    "direction": "horizontal",
    "width": 200
  },
  "right": {
    "id": "7a43a6c530e72e44",
    "type": "split",
    "children": [
      {
        "id": "ea89fdbc5439f479",
        "type": "tabs",
        "dimension": 27.063106796116504,
        "children": [
          {
            "id": "90d026528dc7103b",
            "type": "leaf",
            "pane-relief:history-v1": {
              "pos": 0,
              "stack": [
                {
                  "state": "{}",
                  "eState": "{}"
                }
              ]
            },
            "state": {
              "type": "outline",
              "state": {
                "file": "Atlas/Notes/Ideas/Programming/Networking/Network Components.md"
              },
              "icon": "lucide-list",
              "title": "Outline of Network Components"
            }
          },
          {
            "id": "8ca68f20a1fff78e",
            "type": "leaf",
            "pane-relief:history-v1": {
              "pos": 0,
              "stack": [
                {
                  "state": "{}",
                  "eState": "{}"
                }
              ]
            },
            "state": {
              "type": "all-properties",
              "state": {
                "sortOrder": "frequency",
                "showSearch": false,
                "searchQuery": ""
              },
              "icon": "lucide-archive",
              "title": "All properties"
            }
          },
          {
            "id": "77966b04a7f238ed",
            "type": "leaf",
            "pane-relief:history-v1": {
              "pos": 0,
              "stack": [
                {
                  "state": "{}",
                  "eState": "{}"
                }
              ]
            },
            "state": {
              "type": "search",
              "state": {
                "query": "Relational",
                "matchingCase": false,
                "explainSearch": false,
                "collapseAll": true,
                "extraContext": false,
                "sortOrder": "byModifiedTime"
              },
              "icon": "lucide-search",
              "title": "Search"
            }
          },
          {
            "id": "4f6e4ddebde66a86",
            "type": "leaf",
            "pane-relief:history-v1": {
              "pos": 0,
              "stack": [
                {
                  "state": "{}",
                  "eState": "{}"
                }
              ]
            },
            "state": {
              "type": "tag",
              "state": {
                "sortOrder": "alphabetical",
                "useHierarchy": true
              },
              "icon": "lucide-tags",
              "title": "Tags"
            }
          },
          {
            "id": "1371b66a09c0d426",
            "type": "leaf",
            "pane-relief:history-v1": {
              "pos": 0,
              "stack": [
                {
                  "state": "{}",
                  "eState": "{}"
                }
              ]
            },
            "state": {
              "type": "git-view",
              "state": {},
              "icon": "git-pull-request",
              "title": "Source Control"
            }
          },
          {
            "id": "81a222858f8a142d",
            "type": "leaf",
            "pane-relief:history-v1": {
              "pos": 0,
              "stack": [
                {
                  "state": "{}",
                  "eState": "{}"
                }
              ]
            },
            "state": {
              "type": "review-queue-list-view",
              "state": {},
              "icon": "SpacedRepIcon",
              "title": "Notes Review Queue"
            }
          }
        ],
        "currentTab": 5
      },
      {
        "id": "3d767c407ab4c865",
        "type": "tabs",
        "dimension": 45.75242718446602,
        "children": [
          {
            "id": "c3f1ee10bb319298",
            "type": "leaf",
            "pane-relief:history-v1": {
              "pos": 0,
              "stack": [
                {
                  "state": "{}",
                  "eState": "{}"
                }
              ]
            },
            "state": {
              "type": "localgraph",
              "state": {
                "file": "+/Subnetting.md",
                "options": {
                  "collapse-filter": true,
                  "search": "",
                  "localJumps": 1,
                  "localBacklinks": true,
                  "localForelinks": true,
                  "localInterlinks": false,
                  "showTags": false,
                  "showAttachments": false,
                  "hideUnresolved": false,
                  "collapse-color-groups": true,
                  "colorGroups": [],
                  "collapse-display": false,
                  "showArrow": true,
                  "textFadeMultiplier": 0,
                  "nodeSizeMultiplier": 1,
                  "lineSizeMultiplier": 1,
                  "collapse-forces": true,
                  "centerStrength": 0.518713248970312,
                  "repelStrength": 10,
                  "linkStrength": 1,
                  "linkDistance": 250,
                  "scale": 0.7514342322277636,
                  "close": true
                }
              },
              "icon": "lucide-git-fork",
              "title": "Graph of Subnetting"
            }
          }
        ]
      },
      {
        "id": "8e15cd93a6a4be64",
        "type": "tabs",
        "dimension": 27.184466019417474,
        "children": [
          {
            "id": "d535bd36dbc98e0b",
            "type": "leaf",
            "pane-relief:history-v1": {
              "pos": 0,
              "stack": [
                {
                  "state": "{}",
                  "eState": "{}"
                }
              ]
            },
            "state": {
              "type": "backlink",
              "state": {
                "file": "+/Subnetting.md",
                "collapseAll": true,
                "extraContext": false,
                "sortOrder": "byCreatedTimeReverse",
                "showSearch": false,
                "searchQuery": "",
                "backlinkCollapsed": false,
                "unlinkedCollapsed": true
              },
              "icon": "links-coming-in",
              "title": "Backlinks for Subnetting"
            }
          },
          {
            "id": "ae0aed29d208c352",
            "type": "leaf",
            "pane-relief:history-v1": {
              "pos": 0,
              "stack": [
                {
                  "state": "{}",
                  "eState": "{}"
                }
              ]
            },
            "state": {
              "type": "outgoing-link",
              "state": {
                "file": "+/DBAPI Middlewares.md",
                "linksCollapsed": false,
                "unlinkedCollapsed": true
              },
              "icon": "links-going-out",
              "title": "Outgoing links from DBAPI Middlewares"
            }
          },
          {
            "id": "08676cd662407217",
            "type": "leaf",
            "pane-relief:history-v1": {
              "pos": 0,
              "stack": [
                {
                  "state": "{}",
                  "eState": "{}"
                }
              ]
            },
            "state": {
              "type": "outline",
              "state": {
                "file": "+/DBAPI Middlewares.md"
              },
              "icon": "lucide-list",
              "title": "Outline of DBAPI Middlewares"
            }
          }
        ]
      }
    ],
    "direction": "horizontal",
    "width": 277.5,
    "collapsed": true
  },
  "left-ribbon": {
    "hiddenItems": {
      "daily-notes:Open today's daily note": false,
      "publish:Publish changes...": false,
      "switcher:Open quick switcher": false,
      "command-palette:Open command palette": false,
      "templates:Insert template": false,
      "graph:Open graph view": false,
      "canvas:Create new canvas": false,
      "workspaces:Manage workspace layouts": false,
      "periodic-notes:Open today's daily note": false,
      "darlal-switcher-plus:Open in Headings Mode": false,
      "darlal-switcher-plus:Open Symbols for the active editor": false,
      "callout-manager:Insert Callout": false,
      "obsidian-spaced-repetition:Review flashcards": false,
      "obsidian-git:Open Git source control": false,
      "cmdr:Toggle stacked tabs": false,
      "obsidian42-brat:BRAT": false,
      "obsidian-excalidraw-plugin:Create new drawing": false
    }
  },
  "active": "dffaac5fd2a5f56c",
  "ophidian:layout-settings": {
    "pane-relief:focus-lock": false
  },
  "lastOpenFiles": [
    "Atlas/Maps/Networking Fundamentals.md",
    "Atlas/Notes/Ideas/Programming/Networking/Types of Networks.md",
    "+/Normalization.md",
    "+/الطريقة الخمسينية لحفظ القرآن.md",
    "+/Subnetting.md",
    "Atlas/Utilities/Images/Pasted image 20241115142110.png",
    "Atlas/Maps/Database MOC.md",
    "Atlas/Utilities/Images/Pasted image 20241115132511.png.~tmp",
    "Atlas/Utilities/Images/Pasted image 20241115132511.png",
    "Atlas/Utilities/Images/Pasted image 20241115131513.png",
    "Atlas/Utilities/Images/Pasted image 20241115131144.png",
    "Atlas/Notes/Ideas/Programming/Networking/IP Address.md",
    "Atlas/Notes/Ideas/Programming/Networking/TCP-IP.md",
    "Atlas/Utilities/Images/Pasted image 20241114204506.png",
    "Atlas/Utilities/Images/Pasted image 20241114201926.png",
    "Atlas/Utilities/Images/Pasted image 20241114201415.png",
    "Atlas/Utilities/Images/Pasted image 20241114201406.png",
    "Atlas/Utilities/Images/Pasted image 20241114201328.png",
    "Atlas/Utilities/Images/Pasted image 20241114200619.png",
    "Atlas/Notes/Outputs/OSI model - Article.md",
    "+/What is TCP-IP.md",
    "Atlas/Notes/Ideas/Programming/Networking/How the web works-CornPop.md",
    "Atlas/Notes/Ideas/Programming/Networking/How the web works.md",
    "Atlas/Notes/Ideas/Programming/Networking/Network Components.md",
    "Atlas/Notes/Ideas/Programming/Networking/OSI model.md",
    "+/Internetworking.md",
    "Atlas/Notes/Ideas/Programming/Networking/Network.md",
    "Atlas/Notes/Ideas/Programming/Networking/Client-Server Architecture.md",
    "Atlas/Utilities/Images/Pasted image 20240721115816.png.~tmp",
    "+/Networking Fundamentals.md",
    "+/Get Product by Id Endpoint.md",
    "Atlas/Notes/Ideas/Programming/DotNet/ASP/Asp DotNet Core Web API.md",
    "Atlas/Notes/Ideas/Programming/DotNet/ASP/Web API/Get Products Endpoint.md",
    "Atlas/Notes/Ideas/Programming/DotNet/ASP/Web API/Postman.md",
    "Atlas/Notes/Ideas/Programming/DotNet/ASP/Web API/DNAPI Project Anatomy.md",
    "Atlas/Notes/Ideas/Programming/DotNet/ASP/Web API/DNAPI Introduction.md",
    "+/فكرة - بودكاست عادي.md",
    "Atlas/Notes/Ideas/Programming/DotNet/ASP/Web API/Saving data from database in memory.md",
    "Atlas/Notes/Sources/PDFs/Distributed Systems/lec2 part2 distributed systems.pdf",
    "Atlas/Notes/Sources/PDFs/Distributed Systems/lec2 part1 distributed systems.pdf",
    "Atlas/Notes/Sources/PDFs/Distributed Systems/lec1 distributed systems.pdf",
    "Atlas/Notes/Sources/PDFs/Distributed Systems",
    "Atlas/Utilities/Images/Pasted image 20241025102627.png.~tmp",
    "Atlas/Notes/Ideas/Programming/More",
    "Atlas/Notes/Ideas/Programming/Map your mind",
    "Atlas/Utilities/Images/Pasted image 20241111052946.png.~tmp",
    "Atlas/Notes/Ideas/القرآن الكريم/Untitled.canvas",
    "Atlas/Notes/Ideas/Untitled.canvas",
    "Atlas/Utilities/Canvases/2023-03-20 - Review, Brain Dump, Imagine, Prioritize.canvas",
    "Atlas/Utilities/Canvases/LYT W10 Calendar Canvas.canvas",
    "Atlas/Utilities/Canvases/LYT Ship Dashboard.canvas",
    "Atlas/Utilities/Canvases/LYT W11 Calendar Canvas.canvas",
    "Atlas/Utilities/Canvases/Obsidian Canvas MOC.canvas",
    "Atlas/Utilities/Canvases/Ship of the Sensemaker.canvas",
    "Atlas/Utilities/Canvases/LYT 2023 Rules.canvas",
    "Atlas/Utilities/Canvases/LYT Book Framing.canvas"
  ]
}