{
  "main": {
    "id": "c4f7fdb608baf8e1",
    "type": "split",
    "children": [
      {
        "id": "e0b3ac0111659cd1",
        "type": "tabs",
        "children": [
          {
            "id": "11bdb289d28a6708",
            "type": "leaf",
            "pane-relief:history-v1": {
              "pos": 0,
              "stack": [
                {
                  "state": "{}",
                  "eState": "{}"
                }
              ]
            },
            "pinned": true,
            "state": {
              "type": "markdown",
              "state": {
                "file": "Home.md",
                "mode": "preview",
                "backlinks": true,
                "source": false
              },
              "pinned": true,
              "icon": "lucide-file",
              "title": "Home"
            }
          },
          {
            "id": "a712844f471d7de6",
            "type": "leaf",
            "pane-relief:history-v1": {
              "pos": 0,
              "stack": [
                {
                  "state": "{}",
                  "eState": "{}"
                },
                {
                  "title": "CSharp MOC",
                  "icon": "lucide-file",
                  "state": "{\"type\":\"markdown\",\"state\":{\"file\":\"Atlas/Maps/CSharp MOC.md\",\"mode\":\"source\",\"backlinks\":true,\"source\":false},\"icon\":\"lucide-file\",\"title\":\"CSharp MOC\"}",
                  "eState": "{\"cursor\":{\"from\":{\"line\":78,\"ch\":10},\"to\":{\"line\":78,\"ch\":10}},\"scroll\":36.479166666666664}"
                },
                {
                  "title": "DotNet",
                  "icon": "lucide-file",
                  "state": "{\"type\":\"markdown\",\"state\":{\"file\":\"Atlas/Maps/DotNet.md\",\"mode\":\"source\",\"backlinks\":true,\"source\":false},\"icon\":\"lucide-file\",\"title\":\"DotNet\"}",
                  "eState": "{\"cursor\":{\"from\":{\"line\":11,\"ch\":12},\"to\":{\"line\":11,\"ch\":12}}}"
                },
                {
                  "title": "Asp DotNet Core",
                  "icon": "lucide-file",
                  "state": "{\"type\":\"markdown\",\"state\":{\"file\":\"Atlas/Notes/Ideas/Programming/DotNet/ASP/Asp DotNet Core.md\",\"mode\":\"source\",\"backlinks\":true,\"source\":false},\"icon\":\"lucide-file\",\"title\":\"Asp DotNet Core\"}",
                  "eState": "{\"cursor\":{\"from\":{\"line\":6,\"ch\":0},\"to\":{\"line\":6,\"ch\":0}}}"
                },
                {
                  "title": "Asp DotNet Core Web API",
                  "icon": "lucide-file",
                  "state": "{\"type\":\"markdown\",\"state\":{\"file\":\"Atlas/Notes/Ideas/Programming/DotNet/ASP/Asp DotNet Core Web API.md\",\"mode\":\"source\",\"backlinks\":true,\"source\":false},\"icon\":\"lucide-file\",\"title\":\"Asp DotNet Core Web API\"}",
                  "eState": "{\"cursor\":{\"from\":{\"line\":8,\"ch\":0},\"to\":{\"line\":8,\"ch\":0}}}"
                },
                {
                  "title": "DBAPI Action Filters",
                  "icon": "lucide-file",
                  "state": "{\"type\":\"markdown\",\"state\":{\"file\":\"+/DBAPI Action Filters.md\",\"mode\":\"source\",\"backlinks\":true,\"source\":false},\"icon\":\"lucide-file\",\"title\":\"DBAPI Action Filters\"}",
                  "eState": "{\"cursor\":{\"from\":{\"line\":6,\"ch\":0},\"to\":{\"line\":6,\"ch\":0}},\"scroll\":6}"
                },
                {
                  "title": "Asp DotNet Core Web API",
                  "icon": "lucide-file",
                  "state": "{\"type\":\"markdown\",\"state\":{\"file\":\"Atlas/Notes/Ideas/Programming/DotNet/ASP/Asp DotNet Core Web API.md\",\"mode\":\"source\",\"backlinks\":true,\"source\":false},\"icon\":\"lucide-file\",\"title\":\"Asp DotNet Core Web API\"}",
                  "eState": "{\"cursor\":{\"from\":{\"line\":16,\"ch\":21},\"to\":{\"line\":16,\"ch\":21}},\"scroll\":8}"
                },
                {
                  "title": "DotNet",
                  "icon": "lucide-file",
                  "state": "{\"type\":\"markdown\",\"state\":{\"file\":\"Atlas/Maps/DotNet.md\",\"mode\":\"source\",\"backlinks\":true,\"source\":false},\"icon\":\"lucide-file\",\"title\":\"DotNet\"}",
                  "eState": "{\"cursor\":{\"from\":{\"line\":13,\"ch\":11},\"to\":{\"line\":13,\"ch\":11}},\"scroll\":8}"
                },
                {
                  "title": "Back-end MOC",
                  "icon": "lucide-file",
                  "state": "{\"type\":\"markdown\",\"state\":{\"file\":\"Atlas/Maps/Back-end MOC.md\",\"mode\":\"source\",\"backlinks\":true,\"source\":false},\"icon\":\"lucide-file\",\"title\":\"Back-end MOC\"}",
                  "eState": "{\"cursor\":{\"from\":{\"line\":22,\"ch\":5},\"to\":{\"line\":22,\"ch\":5}},\"scroll\":8}"
                },
                {
                  "title": "Programming MOC",
                  "icon": "lucide-file",
                  "state": "{\"type\":\"markdown\",\"state\":{\"file\":\"Atlas/Maps/Programming MOC.md\",\"mode\":\"source\",\"backlinks\":true,\"source\":false},\"icon\":\"lucide-file\",\"title\":\"Programming MOC\"}",
                  "eState": "{\"cursor\":{\"from\":{\"line\":39,\"ch\":11},\"to\":{\"line\":39,\"ch\":11}},\"scroll\":24.553066666666666}"
                },
                {
                  "title": "Library",
                  "icon": "lucide-file",
                  "state": "{\"type\":\"markdown\",\"state\":{\"file\":\"Atlas/Maps/Library.md\",\"mode\":\"source\",\"backlinks\":true,\"source\":false},\"icon\":\"lucide-file\",\"title\":\"Library\"}",
                  "eState": "{\"cursor\":{\"from\":{\"line\":8,\"ch\":0},\"to\":{\"line\":8,\"ch\":0}},\"scroll\":17.472646001360413}"
                }
              ]
            },
            "state": {
              "type": "markdown",
              "state": {
                "file": "Atlas/Notes/Ideas/Programming/DotNet/CSharp/Cs Generics.md",
                "mode": "source",
                "backlinks": true,
                "source": false
              },
              "icon": "lucide-file",
              "title": "Cs Generics"
            }
          }
        ],
        "currentTab": 1
      }
    ],
    "direction": "vertical"
  },
  "left": {
    "id": "440b3841429709ed",
    "type": "split",
    "children": [
      {
        "id": "b208c03cadd231ee",
        "type": "tabs",
        "dimension": 54.02597402597402,
        "children": [
          {
            "id": "dddbab8b18fd423a",
            "type": "leaf",
            "pane-relief:history-v1": {
              "pos": 0,
              "stack": [
                {
                  "state": "{}",
                  "eState": "{}"
                }
              ]
            },
            "state": {
              "type": "file-explorer",
              "state": {
                "sortOrder": "byCreatedTime"
              },
              "icon": "lucide-folder-closed",
              "title": "Files"
            }
          }
        ]
      },
      {
        "id": "f20ae5728f14bb8d",
        "type": "tabs",
        "dimension": 45.97402597402597,
        "children": [
          {
            "id": "bfacbb72bba173bf",
            "type": "leaf",
            "pane-relief:history-v1": {
              "pos": 0,
              "stack": [
                {
                  "state": "{}",
                  "eState": "{}"
                }
              ]
            },
            "state": {
              "type": "recent-files",
              "state": {},
              "icon": "clock",
              "title": "Recent Files"
            }
          },
          {
            "id": "1dc0cb1cebc39098",
            "type": "leaf",
            "pane-relief:history-v1": {
              "pos": 0,
              "stack": [
                {
                  "state": "{}",
                  "eState": "{}"
                }
              ]
            },
            "state": {
              "type": "calendar",
              "state": {},
              "icon": "calendar-with-checkmark",
              "title": "Calendar"
            }
          }
        ]
      }
    ],
    "direction": "horizontal",
    "width": 200
  },
  "right": {
    "id": "7a43a6c530e72e44",
    "type": "split",
    "children": [
      {
        "id": "ea89fdbc5439f479",
        "type": "tabs",
        "dimension": 27.063106796116504,
        "children": [
          {
            "id": "90d026528dc7103b",
            "type": "leaf",
            "pane-relief:history-v1": {
              "pos": 0,
              "stack": [
                {
                  "state": "{}",
                  "eState": "{}"
                }
              ]
            },
            "state": {
              "type": "outline",
              "state": {
                "file": "Atlas/Notes/Ideas/Programming/Python/Py Format for print.md"
              },
              "icon": "lucide-list",
              "title": "Outline of Py Format for print"
            }
          },
          {
            "id": "77966b04a7f238ed",
            "type": "leaf",
            "pane-relief:history-v1": {
              "pos": 0,
              "stack": [
                {
                  "state": "{}",
                  "eState": "{}"
                }
              ]
            },
            "state": {
              "type": "search",
              "state": {
                "query": "\"DNS\"",
                "matchingCase": false,
                "explainSearch": false,
                "collapseAll": true,
                "extraContext": false,
                "sortOrder": "byModifiedTime"
              },
              "icon": "lucide-search",
              "title": "Search"
            }
          },
          {
            "id": "4f6e4ddebde66a86",
            "type": "leaf",
            "pane-relief:history-v1": {
              "pos": 0,
              "stack": [
                {
                  "state": "{}",
                  "eState": "{}"
                }
              ]
            },
            "state": {
              "type": "tag",
              "state": {
                "sortOrder": "alphabetical",
                "useHierarchy": true
              },
              "icon": "lucide-tags",
              "title": "Tags"
            }
          },
          {
            "id": "8ca68f20a1fff78e",
            "type": "leaf",
            "pane-relief:history-v1": {
              "pos": 0,
              "stack": [
                {
                  "state": "{}",
                  "eState": "{}"
                }
              ]
            },
            "state": {
              "type": "all-properties",
              "state": {
                "sortOrder": "frequency",
                "showSearch": false,
                "searchQuery": ""
              },
              "icon": "lucide-archive",
              "title": "All properties"
            }
          },
          {
            "id": "1371b66a09c0d426",
            "type": "leaf",
            "pane-relief:history-v1": {
              "pos": 0,
              "stack": [
                {
                  "state": "{}",
                  "eState": "{}"
                }
              ]
            },
            "state": {
              "type": "git-view",
              "state": {},
              "icon": "git-pull-request",
              "title": "Source Control"
            }
          },
          {
            "id": "777a14ab1a13cce9",
            "type": "leaf",
            "pane-relief:history-v1": {
              "pos": 0,
              "stack": [
                {
                  "state": "{}",
                  "eState": "{}"
                }
              ]
            },
            "state": {
              "type": "review-queue-list-view",
              "state": {},
              "icon": "lucide-file",
              "title": "Plugin no longer active"
            }
          },
          {
            "id": "b3650e5885726e88",
            "type": "leaf",
            "pane-relief:history-v1": {
              "pos": 0,
              "stack": [
                {
                  "state": "{}",
                  "eState": "{}"
                }
              ]
            },
            "state": {
              "type": "review-queue-list-view",
              "state": {},
              "icon": "lucide-file",
              "title": "Plugin no longer active"
            }
          },
          {
            "id": "6941d5104944566a",
            "type": "leaf",
            "pane-relief:history-v1": {
              "pos": 0,
              "stack": [
                {
                  "state": "{}",
                  "eState": "{}"
                }
              ]
            },
            "state": {
              "type": "review-queue-list-view",
              "state": {},
              "icon": "lucide-file",
              "title": "Plugin no longer active"
            }
          },
          {
            "id": "3039fe66792d5778",
            "type": "leaf",
            "pane-relief:history-v1": {
              "pos": 0,
              "stack": [
                {
                  "state": "{}",
                  "eState": "{}"
                }
              ]
            },
            "state": {
              "type": "review-queue-list-view",
              "state": {},
              "icon": "SpacedRepIcon",
              "title": "Notes Review Queue"
            }
          },
          {
            "id": "f88b2425da3bb0e7",
            "type": "leaf",
            "pane-relief:history-v1": {
              "pos": 0,
              "stack": [
                {
                  "state": "{}",
                  "eState": "{}"
                }
              ]
            },
            "state": {
              "type": "review-queue-list-view",
              "state": {},
              "icon": "SpacedRepIcon",
              "title": "Notes Review Queue"
            }
          }
        ],
        "currentTab": 9
      },
      {
        "id": "3d767c407ab4c865",
        "type": "tabs",
        "dimension": 45.75242718446602,
        "children": [
          {
            "id": "c3f1ee10bb319298",
            "type": "leaf",
            "pane-relief:history-v1": {
              "pos": 0,
              "stack": [
                {
                  "state": "{}",
                  "eState": "{}"
                }
              ]
            },
            "state": {
              "type": "localgraph",
              "state": {
                "file": "Atlas/Notes/Ideas/Programming/DotNet/CSharp/Cs Generics.md",
                "options": {
                  "collapse-filter": true,
                  "search": "",
                  "localJumps": 1,
                  "localBacklinks": true,
                  "localForelinks": true,
                  "localInterlinks": false,
                  "showTags": false,
                  "showAttachments": false,
                  "hideUnresolved": false,
                  "collapse-color-groups": true,
                  "colorGroups": [],
                  "collapse-display": false,
                  "showArrow": true,
                  "textFadeMultiplier": 0,
                  "nodeSizeMultiplier": 1,
                  "lineSizeMultiplier": 1,
                  "collapse-forces": true,
                  "centerStrength": 0.518713248970312,
                  "repelStrength": 10,
                  "linkStrength": 1,
                  "linkDistance": 250,
                  "scale": 0.5359795996225959,
                  "close": true
                }
              },
              "icon": "lucide-git-fork",
              "title": "Graph of Cs Generics"
            }
          }
        ]
      },
      {
        "id": "8e15cd93a6a4be64",
        "type": "tabs",
        "dimension": 27.184466019417474,
        "children": [
          {
            "id": "d535bd36dbc98e0b",
            "type": "leaf",
            "pane-relief:history-v1": {
              "pos": 0,
              "stack": [
                {
                  "state": "{}",
                  "eState": "{}"
                }
              ]
            },
            "state": {
              "type": "backlink",
              "state": {
                "file": "Atlas/Notes/Ideas/Programming/DotNet/CSharp/Cs Generics.md",
                "collapseAll": true,
                "extraContext": false,
                "sortOrder": "byCreatedTimeReverse",
                "showSearch": false,
                "searchQuery": "",
                "backlinkCollapsed": false,
                "unlinkedCollapsed": true
              },
              "icon": "links-coming-in",
              "title": "Backlinks for Cs Generics"
            }
          },
          {
            "id": "ae0aed29d208c352",
            "type": "leaf",
            "pane-relief:history-v1": {
              "pos": 0,
              "stack": [
                {
                  "state": "{}",
                  "eState": "{}"
                }
              ]
            },
            "state": {
              "type": "outgoing-link",
              "state": {
                "file": "+/DBAPI Middlewares.md",
                "linksCollapsed": false,
                "unlinkedCollapsed": true
              },
              "icon": "links-going-out",
              "title": "Outgoing links from DBAPI Middlewares"
            }
          },
          {
            "id": "08676cd662407217",
            "type": "leaf",
            "pane-relief:history-v1": {
              "pos": 0,
              "stack": [
                {
                  "state": "{}",
                  "eState": "{}"
                }
              ]
            },
            "state": {
              "type": "outline",
              "state": {
                "file": "+/DBAPI Middlewares.md"
              },
              "icon": "lucide-list",
              "title": "Outline of DBAPI Middlewares"
            }
          }
        ]
      }
    ],
    "direction": "horizontal",
    "width": 321.5
  },
  "left-ribbon": {
    "hiddenItems": {
      "daily-notes:Open today's daily note": false,
      "publish:Publish changes...": false,
      "switcher:Open quick switcher": false,
      "command-palette:Open command palette": false,
      "templates:Insert template": false,
      "graph:Open graph view": false,
      "canvas:Create new canvas": false,
      "workspaces:Manage workspace layouts": false,
      "periodic-notes:Open today's daily note": false,
      "darlal-switcher-plus:Open in Headings Mode": false,
      "darlal-switcher-plus:Open Symbols for the active editor": false,
      "obsidian-excalidraw-plugin:Create new drawing": false,
      "callout-manager:Insert Callout": false,
      "obsidian42-brat:BRAT": false,
      "obsidian-spaced-repetition:Review flashcards": false,
      "obsidian-git:Open Git source control": false,
      "cmdr:Toggle stacked tabs": false
    }
  },
  "active": "a712844f471d7de6",
  "lastOpenFiles": [
    "Atlas/Maps/CSharp MOC.md",
    "Atlas/Maps/DotNet.md",
    "Atlas/Notes/Ideas/Programming/DotNet/ASP/Asp DotNet Core.md",
    "Atlas/Notes/Ideas/Programming/DotNet/ASP/Asp DotNet Core Web API.md",
    "+/DBAPI Action Filters.md",
    "Atlas/Maps/Python MOC.md",
    "Atlas/Notes/Ideas/Programming/Python/Py Format for print.md",
    "Atlas/Notes/Ideas/Programming/DotNet/ASP/Web API/DBAPI Middlewares.md",
    "+/Py Abstraction.md",
    "Atlas/Utilities/Images/Pasted image 20241021051718.png.~tmp",
    "Atlas/Utilities/Images/Pasted image 20241021051718.png",
    "Atlas/Notes/Ideas/Programming/DotNet/ASP/Web API/DNAPI Basic CRUD Operations.md",
    "Atlas/Notes/Ideas/Programming/DotNet/ASP/Web API/DNAPI Project Anatomy.md",
    "Atlas/Maps/Back-end MOC.md",
    "Atlas/Maps/Programming MOC.md",
    "Home.md",
    "Atlas/Maps/Data Structure and Algorithms MOC.md",
    "Atlas/Maps/Library.md",
    "Atlas/Notes/Ideas/Programming/Networking/HTTP.md",
    "Atlas/Utilities/Images/Pasted image 20241018080329.png.~tmp",
    "Atlas/Utilities/Images/Pasted image 20241018080329.png",
    "Atlas/Notes/Ideas/Programming/DotNet/ASP/Web API/DNAPI Dependency Injection.md",
    "Atlas/Notes/Ideas/Programming/Topics/Web application frameworks.md",
    "Atlas/Notes/Ideas/Programming/DotNet/CSharp/Cs Output.md",
    "Atlas/Notes/Ideas/Programming/Topics/Programming Paradigms.md",
    "+/DNAPI Project Structure.md",
    "Atlas/Maps/SOLID Principles.md",
    "Atlas/Notes/Ideas/Programming/SOLID/Dependency Inversion Principle (DIP).md",
    "Atlas/Utilities/Images/Pasted image 20241017002945.png",
    "Atlas/Utilities/Images/Pasted image 20241017002920.png",
    "Atlas/Notes/Ideas/Programming/DotNet/ASP/Web API/DNAPI Introduction.md",
    "Atlas/Utilities/Images/Pasted image 20241016235304.png",
    "Atlas/Utilities/Images/Pasted image 20241016235142.png",
    "Atlas/Notes/Ideas/Programming/Topics/JSON.md",
    "Atlas/Utilities/Images/Pasted image 20241016223130.png",
    "Atlas/Utilities/Images/Pasted image 20241016222956.png",
    "Atlas/Utilities/Images/Pasted image 20241016222623.png",
    "Atlas/Utilities/Images/Pasted image 20241016045609.png",
    "Atlas/Notes/Ideas/Programming/DotNet/ASP/Web API",
    "Atlas/Notes/Ideas/Programming/DotNet/ASP",
    "Atlas/Utilities/Images/Recursion.pdf",
    "cshra",
    "Atlas/Notes/Ideas/Programming/Problem Solving",
    "Atlas/Utilities/Templates",
    "Atlas/Utilities/Images",
    "Atlas/Utilities/Excalidraw",
    "Atlas/Notes/Ideas/القرآن الكريم/Untitled.canvas",
    "Atlas/Notes/Ideas/Untitled.canvas",
    "Atlas/Utilities/Canvases/2023-03-20 - Review, Brain Dump, Imagine, Prioritize.canvas",
    "Atlas/Utilities/Canvases/LYT W10 Calendar Canvas.canvas",
    "Atlas/Utilities/Canvases/LYT Ship Dashboard.canvas",
    "Atlas/Utilities/Canvases/LYT W11 Calendar Canvas.canvas",
    "Atlas/Utilities/Canvases/Obsidian Canvas MOC.canvas",
    "Atlas/Utilities/Canvases/Ship of the Sensemaker.canvas",
    "Atlas/Utilities/Canvases/LYT 2023 Rules.canvas",
    "Atlas/Utilities/Canvases/LYT Book Framing.canvas"
  ]
}